mircat/__init__.py
mircat-1.0.0.dist-info/METADATA
mircat-1.0.0.dist-info/WHEEL
mircat-1.0.0.dist-info/entry_points.txt
mircat-1.0.0.dist-info/licenses/LICENSE
mircat-1.0.0.dist-info/RECORD
