Metadata-Version: 2.4
Name: mircat
Version: 1.0.0
Summary: Mirshahi CT Analysis Toolkit (MirCAT). Convert, Segment, and Quantify CT NIfTI files.
License-File: LICENSE
Requires-Python: <3.12,>=3.10
Requires-Dist: mircat-seg
Requires-Dist: mircat-stats
